{"results":{"results":[],"facets":[]},"query":{"interactive":true,"original":"Tihs is samle tst cotent for automatci","paraphrase":"Tihs is samle tst cotent for automatci","spellchecked":{"corrections":[{"word":"Tihs","suggestions":[{"confidence":86,"value":"Ths"},{"confidence":83,"value":"IHS"},{"confidence":82,"value":"Tights"}]},{"correction":" is "},{"word":"samle","suggestions":[{"confidence":91,"value":"sample"},{"confidence":90,"value":"sale"},{"confidence":90,"value":"same"}]},{"word":"tst","suggestions":[{"confidence":87,"value":"test"},{"confidence":80,"value":"taste"},{"confidence":80,"value":"tests"}]},{"word":"cotent","suggestions":[{"confidence":92,"value":"content"},{"confidence":87,"value":"contents"},{"confidence":83,"value":"contented"}]},{"correction":" for "},{"word":"automatci","suggestions":[{"confidence":91,"value":"automatic"},{"confidence":87,"value":"automatics"},{"confidence":86,"value":"automatize"}]}]}},"session":"4828410c61c9e-9f03-4307-bc8a-7207653bbe79","transactionId":171569995,"priorTransactionId":171569995}